clickhouse_connect/__version__.py
clickhouse_connect/entry_points.py
clickhouse_connect/common.py
clickhouse_connect/__init__.py
clickhouse_connect/json_impl.py
clickhouse_connect/py.typed
clickhouse_connect/cc_sqlalchemy/__init__.py
clickhouse_connect/cc_sqlalchemy/dialect.py
clickhouse_connect/cc_sqlalchemy/inspector.py
clickhouse_connect/cc_sqlalchemy/sql/preparer.py
clickhouse_connect/cc_sqlalchemy/sql/ddlcompiler.py
clickhouse_connect/cc_sqlalchemy/sql/__init__.py
clickhouse_connect/cc_sqlalchemy/ddl/tableengine.py
clickhouse_connect/cc_sqlalchemy/ddl/__init__.py
clickhouse_connect/cc_sqlalchemy/ddl/custom.py
clickhouse_connect/cc_sqlalchemy/datatypes/__init__.py
clickhouse_connect/cc_sqlalchemy/datatypes/sqltypes.py
clickhouse_connect/cc_sqlalchemy/datatypes/base.py
clickhouse_connect/driverc/__init__.py
clickhouse_connect/driverc/npconv.cpython-312-x86_64-linux-gnu.so
clickhouse_connect/driverc/dataconv.cpython-312-x86_64-linux-gnu.so
clickhouse_connect/driverc/buffer.cpython-312-x86_64-linux-gnu.so
clickhouse_connect/driver/compression.py
clickhouse_connect/driver/errors.py
clickhouse_connect/driver/tools.py
clickhouse_connect/driver/insert.py
clickhouse_connect/driver/ddl.py
clickhouse_connect/driver/context.py
clickhouse_connect/driver/dataconv.py
clickhouse_connect/driver/query.py
clickhouse_connect/driver/client.py
clickhouse_connect/driver/asyncclient.py
clickhouse_connect/driver/constants.py
clickhouse_connect/driver/exceptions.py
clickhouse_connect/driver/common.py
clickhouse_connect/driver/__init__.py
clickhouse_connect/driver/binding.py
clickhouse_connect/driver/buffer.py
clickhouse_connect/driver/npquery.py
clickhouse_connect/driver/models.py
clickhouse_connect/driver/transform.py
clickhouse_connect/driver/httputil.py
clickhouse_connect/driver/types.py
clickhouse_connect/driver/npconv.py
clickhouse_connect/driver/external.py
clickhouse_connect/driver/summary.py
clickhouse_connect/driver/tzutil.py
clickhouse_connect_demo-0.8.6.dist-info/top_level.txt
clickhouse_connect_demo-0.8.6.dist-info/RECORD
clickhouse_connect_demo-0.8.6.dist-info/LICENSE
clickhouse_connect_demo-0.8.6.dist-info/entry_points.txt
clickhouse_connect_demo-0.8.6.dist-info/METADATA
clickhouse_connect_demo-0.8.6.dist-info/WHEEL
