Metadata-Version: 2.1
Name: clickhouse-connect-demo
Version: 0.8.6
Summary: ClickHouse Database Core Driver for Python, Pandas, and Superset
Home-page: https://github.com/ClickHouse/clickhouse-connect
Author: ClickHouse Inc.
Author-email: clients@clickhouse.com
License: Apache License 2.0
Keywords: clickhouse,superset,sqlalchemy,http,driver
Classifier: Development Status :: 4 - Beta
Classifier: Intended Audience :: Developers
Classifier: License :: OSI Approved :: Apache Software License
Classifier: Programming Language :: Python :: 3.8
Classifier: Programming Language :: Python :: 3.9
Classifier: Programming Language :: Python :: 3.10
Classifier: Programming Language :: Python :: 3.11
Classifier: Programming Language :: Python :: 3.12
Classifier: Programming Language :: Python :: 3.13
Requires-Python: ~=3.8
License-File: LICENSE
Requires-Dist: certifi
Requires-Dist: urllib3 >=1.26
Requires-Dist: pytz
Requires-Dist: zstandard
Requires-Dist: lz4
Provides-Extra: arrow
Requires-Dist: pyarrow ; extra == 'arrow'
Provides-Extra: numpy
Requires-Dist: numpy ; extra == 'numpy'
Provides-Extra: orjson
Requires-Dist: orjson ; extra == 'orjson'
Provides-Extra: pandas
Requires-Dist: pandas ; extra == 'pandas'
Provides-Extra: sqlalchemy
Requires-Dist: sqlalchemy <2.0,>1.3.21 ; extra == 'sqlalchemy'
Provides-Extra: tzlocal
Requires-Dist: tzlocal >=4.0 ; extra == 'tzlocal'
